setup.py
calyxhealth/__init__.py
calyxhealth.egg-info/PKG-INFO
calyxhealth.egg-info/SOURCES.txt
calyxhealth.egg-info/dependency_links.txt
calyxhealth.egg-info/top_level.txt