Metadata-Version: 1.0
Name: calyxhealth
Version: 0.1
Summary: library for CalyxHealth.
Home-page: UNKNOWN
Author: calyx
Author-email: admin@calyxhealth.com
License: UNKNOWN
Platform: UNKNOWN
